DESCRIPTION.rst
MANIFEST.in
README.rst
setup.cfg
setup.py
version.txt
kevinarpe_rambutan3.egg-info/PKG-INFO
kevinarpe_rambutan3.egg-info/SOURCES.txt
kevinarpe_rambutan3.egg-info/dependency_links.txt
kevinarpe_rambutan3.egg-info/requires.txt
kevinarpe_rambutan3.egg-info/top_level.txt
rambutan3/RArgs.py
rambutan3/RDelegator.py
rambutan3/RIterableUtil.py
rambutan3/ROpSysUtil.py
rambutan3/RTestUtil.py
rambutan3/RTypes.py
rambutan3/__init__.py
rambutan3/check_args/RCheckArgs.py
rambutan3/check_args/RCheckArgsError.py
rambutan3/check_args/__init__.py
rambutan3/check_args/annotation/ANY.py
rambutan3/check_args/annotation/ANY_VALUE_OF.py
rambutan3/check_args/annotation/BINARY_INPUT_STREAM.py
rambutan3/check_args/annotation/BINARY_OUTPUT_STREAM.py
rambutan3/check_args/annotation/BINARY_SEQUENCE.py
rambutan3/check_args/annotation/BOOL.py
rambutan3/check_args/annotation/BUILTIN_DICT.py
rambutan3/check_args/annotation/BUILTIN_DICT_OF.py
rambutan3/check_args/annotation/BUILTIN_DICT_WHERE_AT_LEAST.py
rambutan3/check_args/annotation/BUILTIN_DICT_WHERE_EXACTLY.py
rambutan3/check_args/annotation/BUILTIN_FROZENSET.py
rambutan3/check_args/annotation/BUILTIN_FROZENSET_OF.py
rambutan3/check_args/annotation/BUILTIN_SET.py
rambutan3/check_args/annotation/BUILTIN_SET_OF.py
rambutan3/check_args/annotation/BYTEARRAY.py
rambutan3/check_args/annotation/BYTES.py
rambutan3/check_args/annotation/CHECKED_FILE_PATH.py
rambutan3/check_args/annotation/CLS.py
rambutan3/check_args/annotation/DICT.py
rambutan3/check_args/annotation/DICT_OF.py
rambutan3/check_args/annotation/DICT_WHERE_AT_LEAST.py
rambutan3/check_args/annotation/DICT_WHERE_EXACTLY.py
rambutan3/check_args/annotation/EXACT_SIZE_BUILTIN_DICT.py
rambutan3/check_args/annotation/EXACT_SIZE_BUILTIN_DICT_OF.py
rambutan3/check_args/annotation/EXACT_SIZE_BUILTIN_FROZENSET.py
rambutan3/check_args/annotation/EXACT_SIZE_BUILTIN_FROZENSET_OF.py
rambutan3/check_args/annotation/EXACT_SIZE_BUILTIN_SET.py
rambutan3/check_args/annotation/EXACT_SIZE_BUILTIN_SET_OF.py
rambutan3/check_args/annotation/EXACT_SIZE_DICT.py
rambutan3/check_args/annotation/EXACT_SIZE_DICT_OF.py
rambutan3/check_args/annotation/EXACT_SIZE_LIST.py
