Metadata-Version: 1.1
Name: kevinarpe-rambutan3
Version: 1.8.0
Summary: Python3 Utilities
Home-page: https://github.com/kevinarpe/kevinarpe-rambutan3
Author: Kevin Connor ARPE
Author-email: kevinarpe@gmail.com
License: UNKNOWN
Keywords: rambutan3 development
Platform: UNKNOWN
Classifier: Development Status :: 5 - Production/Stable
Classifier: Intended Audience :: Developers
Classifier: Topic :: Software Development :: Libraries :: Python Modules
Classifier: License :: OSI Approved :: GNU General Public License v3 or later (GPLv3+)
Classifier: Programming Language :: Python :: 3 :: Only
